LinuxGoujianZhinan/README.md
LinuxGoujianZhinan/__init__.py
LinuxGoujianZhinan/__main__.py
LinuxGoujianZhinan/file.epub
LinuxGoujianZhinan/index.html
LinuxGoujianZhinan/css/__init__.py
LinuxGoujianZhinan/css/annotations.css
LinuxGoujianZhinan/css/main.css
LinuxGoujianZhinan/css/normalize.css
LinuxGoujianZhinan/css/popup.css
LinuxGoujianZhinan/font/__init__.py
LinuxGoujianZhinan/font/fontello.eot
LinuxGoujianZhinan/font/fontello.svg
LinuxGoujianZhinan/font/fontello.ttf
LinuxGoujianZhinan/font/fontello.woff
LinuxGoujianZhinan/img/__init__.py
LinuxGoujianZhinan/img/annotator-glyph-sprite.png
LinuxGoujianZhinan/img/annotator-icon-sprite.png
LinuxGoujianZhinan/img/apple-touch-icon.png
LinuxGoujianZhinan/img/cancelfullscreen.png
LinuxGoujianZhinan/img/close.png
LinuxGoujianZhinan/img/fullscreen.png
LinuxGoujianZhinan/img/loader.gif
LinuxGoujianZhinan/img/menu-icon.png
LinuxGoujianZhinan/img/save.png
LinuxGoujianZhinan/img/saved.png
LinuxGoujianZhinan/img/settings-s.png
LinuxGoujianZhinan/img/settings.png
LinuxGoujianZhinan/img/star.png
LinuxGoujianZhinan/js/__init__.py
LinuxGoujianZhinan/js/epub.js
LinuxGoujianZhinan/js/epub.min.js
LinuxGoujianZhinan/js/epub.min.map
LinuxGoujianZhinan/js/hooks.min.js
LinuxGoujianZhinan/js/hooks.min.map
LinuxGoujianZhinan/js/reader.js
LinuxGoujianZhinan/js/reader.js.map
LinuxGoujianZhinan/js/reader.min.js
LinuxGoujianZhinan/js/reader.min.map
LinuxGoujianZhinan/js/hooks/__init__.py
LinuxGoujianZhinan/js/hooks/extensions/__init__.py
LinuxGoujianZhinan/js/hooks/extensions/highlight.js
LinuxGoujianZhinan/js/libs/__init__.py
LinuxGoujianZhinan/js/libs/jquery.min.js
LinuxGoujianZhinan/js/libs/localforage.min.js
LinuxGoujianZhinan/js/libs/screenfull.js
LinuxGoujianZhinan/js/libs/screenfull.min.js
LinuxGoujianZhinan/js/libs/zip.min.js
LinuxGoujianZhinan/js/plugins/__init__.py
LinuxGoujianZhinan/js/plugins/hypothesis.js
LinuxGoujianZhinan/js/plugins/search.js
linux_goujian_zhinan-2024.3.1.0.dist-info/METADATA
linux_goujian_zhinan-2024.3.1.0.dist-info/WHEEL
linux_goujian_zhinan-2024.3.1.0.dist-info/entry_points.txt
linux_goujian_zhinan-2024.3.1.0.dist-info/top_level.txt
linux_goujian_zhinan-2024.3.1.0.dist-info/RECORD
